karrio/mappers/gls/__init__.py
karrio/mappers/gls/mapper.py
karrio/mappers/gls/proxy.py
karrio/mappers/gls/settings.py
karrio/plugins/gls/__init__.py
karrio/providers/gls/__init__.py
karrio/providers/gls/error.py
karrio/providers/gls/tracking.py
karrio/providers/gls/units.py
karrio/providers/gls/utils.py
karrio/providers/gls/shipment/__init__.py
karrio/providers/gls/shipment/create.py
karrio/schemas/gls/__init__.py
karrio/schemas/gls/error_response.py
karrio/schemas/gls/shipment_request.py
karrio/schemas/gls/shipment_response.py
karrio/schemas/gls/tracking_response.py
karrio_gls-2026.1.4.dist-info/METADATA
karrio_gls-2026.1.4.dist-info/WHEEL
karrio_gls-2026.1.4.dist-info/entry_points.txt
karrio_gls-2026.1.4.dist-info/top_level.txt
karrio_gls-2026.1.4.dist-info/RECORD
